{
  "playerName": "Lucas Terças",
  "name": "Kvothe",
  "surname": "Arliden",
  "race": "Human",
  "class": "Bard",
  "alignment": "Chaotic Neutral",
  "armour": 18,
  "level": 2,
  "maxHealth": 10,
  "curHealth": 2,
  "proficiencyBonus": 2,
  "healing": 4,
  "proficiencies": ["str", "con"],
  "passivePerception": 16,
  "savingThrows": {
    "Strenght": { "value": 5, "proficient": true },
    "Dexterity": { "value": -1, "proficient": false },
    "Constitution": { "value": 4, "proficient": true },
    "Intelligence": { "value": 0, "proficient": false },
    "Wisdom": { "value": 2, "proficient": false },
    "Charisma": { "value": 2, "proficient": false }
  },
  "skills": {
    "Acrobatics": { "value": -1, "ability": "dex", "proficient": false },
    "Animal Handling": { "value": 1, "ability": "wis", "proficient": false },
    "Arcana": { "value": 0, "ability": "int", "proficient": false },
    "Athletics": { "value": 5, "ability": "str", "proficient": true },
    "Deception": { "value": 2, "ability": "cha", "proficient": false },
    "History": { "value": 2, "ability": "int", "proficient": true },
    "Insight": { "value": 1, "ability": "wis", "proficient": false },
    "Intimidation": { "value": 2, "ability": "cha", "proficient": false },
    "Investigation": { "value": 0, "ability": "int", "proficient": false },
    "Medicine": { "value": 1, "ability": "wis", "proficient": false },
    "Nature": { "value": 0, "ability": "int", "proficient": false },
    "Perception": { "value": 3, "ability": "wis", "proficient": true },
    "Perfomance": { "value": 2, "ability": "cha", "proficient": false },
    "Persuation": { "value": 4, "ability": "cha", "proficient": true },
    "Religion": { "value": 0, "ability": "int", "proficient": false },
    "Sleight Of Hand": { "value": -1, "ability": "dex", "proficient": false },
    "Stealth": { "value": -1, "ability": "dex", "proficient": false },
    "Survival": { "value": 1, "ability": "wis", "proficient": false }
  },
  "items": ["Small Sword", "Dagger", "Leather Jacket"],
  "spells": {
    "slots": {
      "Friendship": {
        "used": false
      },
      "Animate Object": {
        "used": true
      }
    },
    "learned_spells": [
      "Friendship",
      "Animate Object",
      "Bestow Curse",
      "Blade Ward"
    ]
  },
  "abilities": {
    "str": {
      "value": 14,
      "mod": 2
    },
    "dex": {
      "value": 10,
      "mod": 0
    },
    "con": {
      "value": 16,
      "mod": 3
    },
    "int": {
      "value": 10,
      "mod": 0
    },
    "wis": {
      "value": 12,
      "mod": 1
    },
    "cha": {
      "value": 18,
      "mod": 4
    }
  }
}
